{
  "updated_at": "2026-03-22T19:00:07.062979",
  "kpis": {
    "faturamento_hoje": 904.35,
    "vendas_hoje": 15,
    "ticket_medio": 60.29,
    "cmv_total": 407.7,
    "lucro_bruto": 496.65,
    "margem_pct_real": 54.9,
    "lucro_por_pedido": 33.11,
    "taxa_ml_total": 120.41,
    "shipping_total": 158.83,
    "faturamento_liquido": 625.11,
    "margem_liquida_pct": 24.0,
    "lucro_liquido": 217.41,
    "vendas_semana": 207,
    "faturamento_semana": 13809.39,
    "ad_spend": 370.0,
    "ad_revenue": 0,
    "organic_revenue": 904.35,
    "acos": 0,
    "tacos": 40.9
  },
  "top5": [
    {
      "vendas": 4,
      "faturamento": 311.6,
      "custo": 143.36,
      "title": "Moletom Masculino Zíper Hugo Jobs Blusa Aberta Com",
      "taxa_ml": 43.64,
      "full_unit_price": 77.9,
      "lucro": 168.24,
      "margem_pct": 54.0,
      "score": 88
    },
    {
      "vendas": 3,
      "faturamento": 149.7,
      "custo": 54.78,
      "title": "Carteira Couro Legítimo Slim 8 Porta Cartões E Cnh",
      "taxa_ml": 20.97,
      "full_unit_price": 49.9,
      "lucro": 94.92,
      "margem_pct": 63.4,
      "score": 86
    },
    {
      "vendas": 1,
      "faturamento": 135.73,
      "custo": 25.0,
      "title": "Perfume Masculino Empire Tradicional 100ml - Hinod",
      "taxa_ml": 23.07,
      "full_unit_price": 135.73,
      "lucro": 110.73,
      "margem_pct": 81.6,
      "score": 82
    },
    {
      "vendas": 1,
      "faturamento": 64.01,
      "custo": 35.84,
      "title": "Conjunto Moletom E Calça Infantil Inverno Quentinh",
      "taxa_ml": 6.38,
      "full_unit_price": 64.01,
      "lucro": 28.17,
      "margem_pct": 44.0,
      "score": 82
    },
    {
      "vendas": 1,
      "faturamento": 64,
      "custo": 35.84,
      "title": "Conjunto Moletom E Calça Infantil Inverno Quentinh",
      "taxa_ml": 6.37,
      "full_unit_price": 64,
      "lucro": 28.16,
      "margem_pct": 44.0,
      "score": 82
    }
  ],
  "categories": [
    {
      "nome": "Vestuário Adult",
      "vendas": 4,
      "faturamento": 311.6,
      "custo": 143.36,
      "taxa_ml": 43.64,
      "pct": 34.5,
      "margem_pct": 54.0
    },
    {
      "nome": "Vestuário Infantil",
      "vendas": 5,
      "faturamento": 259.34,
      "custo": 161.34,
      "taxa_ml": 26.01,
      "pct": 28.7,
      "margem_pct": 37.8
    },
    {
      "nome": "Acessórios",
      "vendas": 5,
      "faturamento": 197.68,
      "custo": 78.0,
      "taxa_ml": 27.69,
      "pct": 21.9,
      "margem_pct": 60.5
    },
    {
      "nome": "Outros",
      "vendas": 1,
      "faturamento": 135.73,
      "custo": 25.0,
      "taxa_ml": 23.07,
      "pct": 15.0,
      "margem_pct": 81.6
    }
  ],
  "chart": {
    "labels": [
      "Seg (16)",
      "Ter (17)",
      "Qua (18)",
      "Qui (19)",
      "Sex (20)",
      "Sáb (21)",
      "Dom (22)"
    ],
    "vendas": [
      29,
      20,
      32,
      41,
      27,
      43,
      13
    ],
    "faturamento": [
      2108.38,
      1226.84,
      2291.0,
      2583.27,
      1751.71,
      2930.66,
      748.55
    ]
  },
  "meta": {
    "seller_id": "694166791",
    "source": "MercadoLivre API v1 — LIVE",
    "total_orders_fetched": 15,
    "pads_campaigns_found": true
  },
  "semana": {
    "vendas": 207,
    "faturamento": 13809.39,
    "taxa_ml": 1737.95,
    "faturamento_menos_taxa": 12071.44,
    "ticket_medio": 66.71,
    "ad_spend": 370.0,
    "ad_revenue": 0,
    "ad_impressions": 0,
    "ad_clicks": 0,
    "organic_revenue": 13809.39,
    "acos": 0,
    "tacos": 2.7
  },
  "mes": {
    "vendas": 1116,
    "faturamento": 73403.35,
    "taxa_ml": 8961.5,
    "faturamento_menos_taxa": 64441.85,
    "ticket_medio": 65.77,
    "ad_spend": 370.0,
    "ad_revenue": 0,
    "ad_impressions": 0,
    "ad_clicks": 0,
    "organic_revenue": 73403.35,
    "acos": 0,
    "tacos": 0.5,
    "chart": {
      "labels": [
        "Dom (01)",
        "Seg (02)",
        "Ter (03)",
        "Qua (04)",
        "Qui (05)",
        "Sex (06)",
        "Sáb (07)",
        "Dom (08)",
        "Seg (09)",
        "Ter (10)",
        "Qua (11)",
        "Qui (12)",
        "Sex (13)",
        "Sáb (14)",
        "Dom (15)",
        "Seg (16)",
        "Ter (17)",
        "Qua (18)",
        "Qui (19)",
        "Sex (20)",
        "Sáb (21)",
        "Dom (22)"
      ],
      "vendas": [
        21,
        65,
        53,
        70,
        67,
        49,
        57,
        55,
        59,
        82,
        76,
        82,
        61,
        56,
        57,
        29,
        20,
        32,
        41,
        27,
        43,
        13
      ],
      "faturamento": [
        1349.93,
        4340.3,
        3229.08,
        4175.69,
        3945.04,
        3094.57,
        4003.46,
        3334.83,
        3925.67,
        5558.88,
        5259.34,
        5534.15,
        4479.78,
        3677.8,
        3786.55,
        2108.38,
        1226.84,
        2291.0,
        2583.27,
        1751.71,
        2930.66,
        748.55
      ]
    }
  }
}