{
  "updated_at": "2026-03-12T23:48:18.025129",
  "kpis": {
    "faturamento_hoje": 4404.14,
    "vendas_hoje": 65,
    "ticket_medio": 67.76,
    "cmv_total": 2062.39,
    "lucro_bruto": 2341.75,
    "margem_pct_real": 53.2,
    "lucro_por_pedido": 36.03,
    "taxa_ml_total": 542.09,
    "shipping_total": 752.98,
    "faturamento_liquido": 3109.07,
    "margem_liquida_pct": 23.8,
    "lucro_liquido": 1046.68,
    "vendas_semana": 454,
    "faturamento_semana": 30294.82,
    "ad_spend": 370.0,
    "ad_revenue": 0,
    "organic_revenue": 4404.14,
    "acos": 0,
    "tacos": 8.4
  },
  "top5": [
    {
      "vendas": 27,
      "faturamento": 1832.49,
      "custo": 967.68,
      "title": "Moletom Masculino Zíper Hugo Jobs Blusa Aberta Com",
      "taxa_ml": 172.39,
      "full_unit_price": 67.87,
      "lucro": 864.81,
      "margem_pct": 47.2,
      "score": 99
    },
    {
      "vendas": 10,
      "faturamento": 695.3,
      "custo": 250.0,
      "title": "Body Splash Afrodite Garden Hinode By Jade Picon 2",
      "taxa_ml": 118.2,
      "full_unit_price": 69.53,
      "lucro": 445.3,
      "margem_pct": 64.0,
      "score": 99
    },
    {
      "vendas": 3,
      "faturamento": 197.97,
      "custo": 107.52,
      "title": "Conjunto Moletom E Calça Infantil Inverno Quentinh",
      "taxa_ml": 27.58,
      "full_unit_price": 65.99,
      "lucro": 90.45,
      "margem_pct": 45.7,
      "score": 86
    },
    {
      "vendas": 2,
      "faturamento": 179.98,
      "custo": 53.82,
      "title": "Kit 3 Calça Moletom Infantil Flanelada Menino Meni",
      "taxa_ml": 25.14,
      "full_unit_price": 89.99,
      "lucro": 126.16,
      "margem_pct": 70.1,
      "score": 84
    },
    {
      "vendas": 2,
      "faturamento": 179.98,
      "custo": 53.82,
      "title": "Kit 3 Calça Moletom Infantil Flanelada Menino Meni",
      "taxa_ml": 25.2,
      "full_unit_price": 89.99,
      "lucro": 126.16,
      "margem_pct": 70.1,
      "score": 84
    }
  ],
  "categories": [
    {
      "nome": "Vestuário Adult",
      "vendas": 28,
      "faturamento": 1912.99,
      "custo": 986.35,
      "taxa_ml": 178.82,
      "pct": 43.4,
      "margem_pct": 48.4
    },
    {
      "nome": "Vestuário Infantil",
      "vendas": 24,
      "faturamento": 1611.16,
      "custo": 753.0,
      "taxa_ml": 220.04,
      "pct": 36.6,
      "margem_pct": 53.3
    },
    {
      "nome": "Outros",
      "vendas": 10,
      "faturamento": 695.3,
      "custo": 250.0,
      "taxa_ml": 118.2,
      "pct": 15.8,
      "margem_pct": 64.0
    },
    {
      "nome": "Acessórios",
      "vendas": 4,
      "faturamento": 184.69,
      "custo": 73.04,
      "taxa_ml": 25.03,
      "pct": 4.2,
      "margem_pct": 60.5
    }
  ],
  "chart": {
    "labels": [
      "Sex (06)",
      "Sáb (07)",
      "Dom (08)",
      "Seg (09)",
      "Ter (10)",
      "Qua (11)",
      "Qui (12)"
    ],
    "vendas": [
      49,
      59,
      56,
      63,
      85,
      77,
      65
    ],
    "faturamento": [
      3094.57,
      4159.25,
      3369.74,
      4179.18,
      5784.61,
      5303.33,
      4404.14
    ]
  },
  "meta": {
    "seller_id": "694166791",
    "source": "MercadoLivre API v1 — LIVE",
    "total_orders_fetched": 66,
    "pads_campaigns_found": true
  },
  "semana": {
    "vendas": 454,
    "faturamento": 30294.82,
    "taxa_ml": 3228.97,
    "faturamento_menos_taxa": 27065.85,
    "ticket_medio": 66.73,
    "ad_spend": 370.0,
    "ad_revenue": 0,
    "ad_impressions": 0,
    "ad_clicks": 0,
    "organic_revenue": 30294.82,
    "acos": 0,
    "tacos": 1.2
  },
  "mes": {
    "vendas": 734,
    "faturamento": 47606.34,
    "taxa_ml": 5897.49,
    "faturamento_menos_taxa": 41708.85,
    "ticket_medio": 64.86,
    "ad_spend": 370.0,
    "ad_revenue": 0,
    "ad_impressions": 0,
    "ad_clicks": 0,
    "organic_revenue": 47606.34,
    "acos": 0,
    "tacos": 0.8,
    "chart": {
      "labels": [
        "Dom (01)",
        "Seg (02)",
        "Ter (03)",
        "Qua (04)",
        "Qui (05)",
        "Sex (06)",
        "Sáb (07)",
        "Dom (08)",
        "Seg (09)",
        "Ter (10)",
        "Qua (11)",
        "Qui (12)"
      ],
      "vendas": [
        21,
        66,
        54,
        70,
        68,
        49,
        59,
        56,
        63,
        85,
        77,
        65
      ],
      "faturamento": [
        1349.93,
        4408.17,
        3296.95,
        4175.69,
        4012.91,
        3094.57,
        4159.25,
        3369.74,
        4179.18,
        5784.61,
        5303.33,
        4404.14
      ]
    }
  }
}