{
  "updated_at": "2026-03-17T10:13:24.661922",
  "kpis": {
    "faturamento_hoje": 34.99,
    "vendas_hoje": 1,
    "ticket_medio": 34.99,
    "cmv_total": 18.26,
    "lucro_bruto": 16.73,
    "margem_pct_real": 47.8,
    "lucro_por_pedido": 16.73,
    "taxa_ml_total": 4.08,
    "shipping_total": 6.65,
    "faturamento_liquido": 24.26,
    "margem_liquida_pct": 17.1,
    "lucro_liquido": 6.0,
    "vendas_semana": 367,
    "faturamento_semana": 25202.37,
    "ad_spend": 370.0,
    "ad_revenue": 0,
    "organic_revenue": 34.99,
    "acos": 0,
    "tacos": 1057.4
  },
  "top5": [
    {
      "vendas": 1,
      "faturamento": 34.99,
      "custo": 18.26,
      "title": "Kit 3 Palmilha Anatômica Conforto Ortopédico Supor",
      "taxa_ml": 4.08,
      "full_unit_price": 34.99,
      "lucro": 16.73,
      "margem_pct": 47.8,
      "score": 82
    }
  ],
  "categories": [
    {
      "nome": "Acessórios",
      "vendas": 1,
      "faturamento": 34.99,
      "custo": 18.26,
      "taxa_ml": 4.08,
      "pct": 100.0,
      "margem_pct": 47.8
    }
  ],
  "chart": {
    "labels": [
      "Qua (11)",
      "Qui (12)",
      "Sex (13)",
      "Sáb (14)",
      "Dom (15)",
      "Seg (16)",
      "Ter (17)"
    ],
    "vendas": [
      76,
      84,
      62,
      56,
      58,
      30,
      1
    ],
    "faturamento": [
      5259.34,
      5669.89,
      4547.65,
      3677.8,
      3854.42,
      2158.28,
      34.99
    ]
  },
  "meta": {
    "seller_id": "694166791",
    "source": "MercadoLivre API v1 — LIVE",
    "total_orders_fetched": 1,
    "pads_campaigns_found": true
  },
  "semana": {
    "vendas": 367,
    "faturamento": 25202.37,
    "taxa_ml": 2826.97,
    "faturamento_menos_taxa": 22375.4,
    "ticket_medio": 68.67,
    "ad_spend": 370.0,
    "ad_revenue": 0,
    "ad_impressions": 0,
    "ad_clicks": 0,
    "organic_revenue": 25202.37,
    "acos": 0,
    "tacos": 1.5
  },
  "mes": {
    "vendas": 952,
    "faturamento": 62624.07,
    "taxa_ml": 7557.13,
    "faturamento_menos_taxa": 55066.94,
    "ticket_medio": 65.78,
    "ad_spend": 370.0,
    "ad_revenue": 0,
    "ad_impressions": 0,
    "ad_clicks": 0,
    "organic_revenue": 62624.07,
    "acos": 0,
    "tacos": 0.6,
    "chart": {
      "labels": [
        "Dom (01)",
        "Seg (02)",
        "Ter (03)",
        "Qua (04)",
        "Qui (05)",
        "Sex (06)",
        "Sáb (07)",
        "Dom (08)",
        "Seg (09)",
        "Ter (10)",
        "Qua (11)",
        "Qui (12)",
        "Sex (13)",
        "Sáb (14)",
        "Dom (15)",
        "Seg (16)",
        "Ter (17)"
      ],
      "vendas": [
        21,
        66,
        53,
        70,
        67,
        49,
        57,
        56,
        61,
        84,
        76,
        84,
        62,
        56,
        58,
        30,
        1
      ],
      "faturamento": [
        1349.93,
        4408.17,
        3229.08,
        4175.69,
        3945.04,
        3094.57,
        4003.46,
        3369.74,
        4061.41,
        5716.74,
        5259.34,
        5669.89,
        4547.65,
        3677.8,
        3854.42,
        2158.28,
        34.99
      ]
    }
  }
}